odoo/addons/shopinvader_product_template_multi_link/README.rst
odoo/addons/shopinvader_product_template_multi_link/__init__.py
odoo/addons/shopinvader_product_template_multi_link/__manifest__.py
odoo/addons/shopinvader_product_template_multi_link/data/ir_exports_line.xml
odoo/addons/shopinvader_product_template_multi_link/i18n/shopinvader_product_template_multi_link.pot
odoo/addons/shopinvader_product_template_multi_link/models/__init__.py
odoo/addons/shopinvader_product_template_multi_link/models/shopinvader_product.py
odoo/addons/shopinvader_product_template_multi_link/models/shopinvader_product_link_mixin.py
odoo/addons/shopinvader_product_template_multi_link/readme/CONTRIBUTORS.rst
odoo/addons/shopinvader_product_template_multi_link/readme/CREDITS.rst
odoo/addons/shopinvader_product_template_multi_link/readme/DESCRIPTION.rst
odoo/addons/shopinvader_product_template_multi_link/static/description/index.html
odoo/addons/shopinvader_product_template_multi_link/tests/__init__.py
odoo/addons/shopinvader_product_template_multi_link/tests/common.py
odoo/addons/shopinvader_product_template_multi_link/tests/test_product.py
odoo14_addon_shopinvader_product_template_multi_link-14.0.1.1.0.dist-info/METADATA
odoo14_addon_shopinvader_product_template_multi_link-14.0.1.1.0.dist-info/WHEEL
odoo14_addon_shopinvader_product_template_multi_link-14.0.1.1.0.dist-info/top_level.txt
odoo14_addon_shopinvader_product_template_multi_link-14.0.1.1.0.dist-info/RECORD
