Metadata-Version: 2.1
Name: odoo14-addon-shopinvader-product-template-multi-link
Version: 14.0.1.1.0
Summary: Shopinvader Product Link
Home-page: https://github.com/shopinvader/odoo-shopinvader
Author: Akretion,GRAP,Camptocamp
License: AGPL-3
Platform: UNKNOWN
Classifier: Programming Language :: Python
Classifier: Framework :: Odoo
Classifier: License :: OSI Approved :: GNU Affero General Public License v3
Requires-Python: >=3.6
Requires-Dist: odoo14-addon-product-template-multi-link
Requires-Dist: odoo14-addon-shopinvader
Requires-Dist: odoo (<14.1dev,>=14.0a)
